yahoo_finance_server/__init__.py
yahoo_finance_server/__main__.py
yahoo_finance_server/helper.py
yahoo_finance_server/server.py
yahoo_finance_server-0.1.1.dist-info/METADATA
yahoo_finance_server-0.1.1.dist-info/WHEEL
yahoo_finance_server-0.1.1.dist-info/entry_points.txt
yahoo_finance_server-0.1.1.dist-info/licenses/LICENSE
yahoo_finance_server-0.1.1.dist-info/RECORD
