Metadata-Version: 2.4
Name: yahoo-finance-server
Version: 0.1.1
Summary: Let your AI get comprehensive stock market data from Yahoo Finance including quotes, news, financials, and more.
Project-URL: Homepage, https://github.com/AgentX-ai/AgentX-mcp-servers
Project-URL: Repository, https://github.com/AgentX-ai/AgentX-mcp-servers
Project-URL: Documentation, https://github.com/AgentX-ai/AgentX-mcp-servers#readme
Project-URL: Issues, https://github.com/AgentX-ai/AgentX-mcp-servers/issues
Author-email: Robin <robin@agentx.so>
License: MIT
License-File: LICENSE
Keywords: ai,finance,market-data,mcp,stocks,trading,yahoo-finance
Classifier: Development Status :: 4 - Beta
Classifier: Intended Audience :: Developers
Classifier: License :: OSI Approved :: MIT License
Classifier: Programming Language :: Python :: 3
Classifier: Programming Language :: Python :: 3.11
Classifier: Programming Language :: Python :: 3.12
Classifier: Topic :: Internet :: WWW/HTTP
Classifier: Topic :: Office/Business :: Financial
Classifier: Topic :: Software Development :: Libraries :: Python Modules
Requires-Python: >=3.11
Requires-Dist: mcp>=1.9.3
Requires-Dist: pandas>=2.0.0
Requires-Dist: requests>=2.31.0
Requires-Dist: yfinance==0.2.62
